ifc_graph/__init__.py
ifc_graph/cli.py
ifc_graph/element_filter.py
ifc_graph/neo4j_store.py
ifc_graph/query_loader.py
ifc_graph/cypher_queries/clear_database.cypher
ifc_graph/cypher_queries/create_aggregates_batch.cypher
ifc_graph/cypher_queries/create_elements_batch.cypher
ifc_graph/cypher_queries/create_materials_batch.cypher
ifc_graph/cypher_queries/create_metadata.cypher
ifc_graph/cypher_queries/create_project.cypher
ifc_graph/cypher_queries/create_project_contains.cypher
ifc_graph/cypher_queries/create_property_sets_batch.cypher
ifc_graph/cypher_queries/create_relationships_batch.cypher
ifc_graph/cypher_queries/create_structure_contains.cypher
ifc_graph/cypher_queries/create_structures_batch.cypher
ifc_graph-0.1.3.dist-info/licenses/LICENSE
ifc_graph-0.1.3.dist-info/METADATA
ifc_graph-0.1.3.dist-info/WHEEL
ifc_graph-0.1.3.dist-info/entry_points.txt
ifc_graph-0.1.3.dist-info/top_level.txt
ifc_graph-0.1.3.dist-info/RECORD
