Metadata-Version: 2.4
Name: ifc-graph
Version: 0.1.3
Summary: Convert IFC BIM models to Neo4j graph database for querying building information
Author-email: James Mugo <deeplearningcentral@gmail.com>
Maintainer-email: James Mugo <deeplearningcentral@gmail.com>
License-Expression: MIT
Project-URL: Homepage, https://github.com/mugojames254/ifc-graph-database
Project-URL: Documentation, https://mugojames254.github.io/ifc-graph-database/
Project-URL: Repository, https://github.com/mugojames254/ifc-graph-database
Project-URL: Issues, https://github.com/mugojames254/ifc-graph-database/issues
Project-URL: Changelog, https://github.com/mugojames254/ifc-graph-database/releases
Keywords: ifc,bim,neo4j,graph-database,building-information-modeling,architecture,construction,aec,ifcopenshell
Classifier: Development Status :: 3 - Alpha
Classifier: Intended Audience :: Developers
Classifier: Intended Audience :: Science/Research
Classifier: Operating System :: OS Independent
Classifier: Programming Language :: Python :: 3
Classifier: Programming Language :: Python :: 3.9
Classifier: Programming Language :: Python :: 3.10
Classifier: Programming Language :: Python :: 3.11
Classifier: Programming Language :: Python :: 3.12
Classifier: Topic :: Scientific/Engineering
Classifier: Topic :: Software Development :: Libraries :: Python Modules
Requires-Python: >=3.9
License-File: LICENSE
Requires-Dist: ifcopenshell>=0.7.0
Requires-Dist: neo4j>=5.0.0
Requires-Dist: pyyaml>=6.0
Requires-Dist: python-dotenv>=1.0.0
Provides-Extra: dev
Requires-Dist: pytest>=7.0; extra == "dev"
Requires-Dist: pytest-cov>=4.0; extra == "dev"
Requires-Dist: pytest-mock>=3.0; extra == "dev"
Requires-Dist: black>=23.0; extra == "dev"
Requires-Dist: ruff>=0.1.0; extra == "dev"
Requires-Dist: mypy>=1.0; extra == "dev"
Provides-Extra: docs
Requires-Dist: mkdocs>=1.5.0; extra == "docs"
Requires-Dist: mkdocs-material>=9.0.0; extra == "docs"
Requires-Dist: mkdocstrings[python]>=0.24.0; extra == "docs"
Requires-Dist: mkdocs-gen-files>=0.5.0; extra == "docs"
Requires-Dist: mkdocs-literate-nav>=0.6.0; extra == "docs"
Dynamic: license-file
